siot/__init__.py
siot/getsub.py
siot/pub.py
siot/pub_sub.py
siot/sub.py
siot-0.1.7.dist-info/METADATA
siot-0.1.7.dist-info/WHEEL
siot-0.1.7.dist-info/top_level.txt
siot-0.1.7.dist-info/RECORD
