Metadata-Version: 2.1
Name: siot
Version: 0.1.7
Summary: A package for siot publish and subscribe
Home-page: https://github.com/luoyufenglalala/DFRobot_siot
Author: luoyufenglalala
Author-email: yufeng.luo@dfrobot.com
Classifier: Programming Language :: Python :: 3
Classifier: License :: OSI Approved :: MIT License
Classifier: Operating System :: OS Independent
Requires-Python: >=3.4
Requires-Dist: paho-mqtt <2.0.0
